chaingrep/__init__.py
chaingrep/auth.py
chaingrep/client.py
chaingrep/constants.py
chaingrep/exceptions.py
chaingrep/api_resources/__init__.py
chaingrep/api_resources/account.py
chaingrep/api_resources/fees.py
chaingrep/api_resources/query.py
chaingrep/api_resources/requester.py
chaingrep/api_resources/transaction.py
chaingrep/utils/__init__.py
chaingrep/utils/common_queries.py
chaingrep/utils/format.py
chaingrep/utils/query_utils.py
chaingrep-0.0.6.dist-info/LICENSE
chaingrep-0.0.6.dist-info/METADATA
chaingrep-0.0.6.dist-info/WHEEL
chaingrep-0.0.6.dist-info/top_level.txt
chaingrep-0.0.6.dist-info/RECORD
