Metadata-Version: 2.1
Name: chaingrep
Version: 0.0.6
Summary: Python bindings for the Chaingrep API
Home-page: https://github.com/chaingrep/chaingrep-py
Author: Chaingrep
Author-email: support@chaingrep.com
License: MIT
Project-URL: Changes, https://github.com/chaingrep/chaingrep-py/blob/main/CHANGELOG.md
Project-URL: Source, https://github.com/chaingrep/chaingrep-py
Project-URL: Documentation, https://docs.chaingrep.com
Keywords: chaingrep api blockchain
Platform: UNKNOWN
Classifier: Intended Audience :: Developers
Classifier: License :: OSI Approved :: MIT License
Classifier: Operating System :: OS Independent
Classifier: Programming Language :: Python
Classifier: Programming Language :: Python :: 3.6
Classifier: Programming Language :: Python :: 3.7
Classifier: Programming Language :: Python :: 3.8
Classifier: Programming Language :: Python :: 3.9
Classifier: Programming Language :: Python :: 3.10
Classifier: Natural Language :: English
Classifier: Topic :: Software Development :: Libraries :: Python Modules
License-File: LICENSE
Requires-Dist: requests (>=2.20) ; python_version >= "3.0"
